odoo8_addon_account_balance_ebp_csv_export-8.0.1.1.0-py2.7-nspkg.pth
odoo_addons/account_balance_ebp_csv_export/__openerp__.py
odoo_addons/account_balance_ebp_csv_export/__init__.py
odoo_addons/account_balance_ebp_csv_export/README.rst
odoo_addons/account_balance_ebp_csv_export/wizard/trial_balance_wizard_view.xml
odoo_addons/account_balance_ebp_csv_export/wizard/trial_balance_wizard.py
odoo_addons/account_balance_ebp_csv_export/wizard/__init__.py
odoo8_addon_account_balance_ebp_csv_export-8.0.1.1.0.dist-info/top_level.txt
odoo8_addon_account_balance_ebp_csv_export-8.0.1.1.0.dist-info/WHEEL
odoo8_addon_account_balance_ebp_csv_export-8.0.1.1.0.dist-info/RECORD
odoo8_addon_account_balance_ebp_csv_export-8.0.1.1.0.dist-info/metadata.json
odoo8_addon_account_balance_ebp_csv_export-8.0.1.1.0.dist-info/DESCRIPTION.rst
odoo8_addon_account_balance_ebp_csv_export-8.0.1.1.0.dist-info/METADATA
odoo8_addon_account_balance_ebp_csv_export-8.0.1.1.0.dist-info/namespace_packages.txt
